pymarkup/__init__.py
pymarkup/builder.py
pymarkup-0.0.1.dist-info/LICENSE
pymarkup-0.0.1.dist-info/METADATA
pymarkup-0.0.1.dist-info/WHEEL
pymarkup-0.0.1.dist-info/top_level.txt
pymarkup-0.0.1.dist-info/RECORD
