Metadata-Version: 2.1
Name: pymarkup
Version: 0.0.1
Summary: A basic internal XML-generating DSL in Python 3.
Home-page: https://github.com/bluepython508/PyMarkup
Author: Ben Soroos
Author-email: ben@soroos.net
License: MIT license
Platform: UNKNOWN
Classifier: Intended Audience :: Developers
Classifier: License :: OSI Approved :: MIT License
Classifier: Operating System :: Unix
Classifier: Operating System :: POSIX
Classifier: Operating System :: Microsoft :: Windows
Classifier: Programming Language :: Python :: 3
Classifier: Programming Language :: Python :: 3.7
Classifier: Programming Language :: Python :: Implementation :: CPython
Classifier: Topic :: Utilities
Provides-Extra: dev
Requires-Dist: pytest; extra == 'dev'
Requires-Dist: black; extra == 'dev'
Requires-Dist: twine; extra == 'dev'
Requires-Dist: sphinx; extra == 'dev'
Requires-Dist: sphinx-rtd-theme; extra == 'dev'
Provides-Extra: docs
Requires-Dist: sphinx; extra == 'docs'
Requires-Dist: sphinx-rtd-theme; extra == 'docs'
Requires-Dist: dataclasses; extra == 'docs'
Provides-Extra: tests
Requires-Dist: pytest; extra == 'tests'
